ellar/__init__.py
ellar/py.typed
ellar/app/__init__.py
ellar/app/context.py
ellar/app/factory.py
ellar/app/lifespan.py
ellar/app/main.py
ellar/auth/__init__.py
ellar/auth/constants.py
ellar/auth/decorators.py
ellar/auth/identity.py
ellar/auth/interceptor.py
ellar/auth/guards/__init__.py
ellar/auth/guards/apikey.py
ellar/auth/guards/auth_required.py
ellar/auth/guards/http.py
ellar/auth/guards/mixin.py
ellar/auth/handlers/__init__.py
ellar/auth/handlers/api_key.py
ellar/auth/handlers/http.py
ellar/auth/handlers/mixin.py
ellar/auth/handlers/model.py
ellar/auth/handlers/schemes/__init__.py
ellar/auth/handlers/schemes/api_key.py
ellar/auth/handlers/schemes/base.py
ellar/auth/handlers/schemes/http.py
ellar/auth/middleware/__init__.py
ellar/auth/middleware/auth.py
ellar/auth/middleware/session.py
ellar/auth/policy/__init__.py
ellar/auth/policy/base.py
ellar/auth/policy/common.py
ellar/auth/services/__init__.py
ellar/auth/services/auth_schemes.py
ellar/auth/services/middleware.py
ellar/auth/session/__init__.py
ellar/auth/session/base.py
ellar/auth/session/cookie_dict.py
ellar/auth/session/options.py
ellar/auth/session/strategy.py
ellar/cache/__init__.py
ellar/cache/decorator.py
ellar/cache/interface.py
ellar/cache/make_key_decorator.py
ellar/cache/model.py
ellar/cache/module.py
ellar/cache/schema.py
ellar/cache/service.py
ellar/cache/backends/__init__.py
ellar/cache/backends/_aio_cache.py.ellar
ellar/cache/backends/base.py
ellar/cache/backends/local_cache.py
ellar/cache/backends/pylib_cache.py
ellar/cache/backends/pymem_cache.py
ellar/cache/backends/serializer.py
ellar/cache/backends/redis/__init__.py
ellar/cache/backends/redis/backend.py
ellar/common/__init__.py
ellar/common/constants.py
ellar/common/converters.py
ellar/common/datastructures.py
ellar/common/logging.py
ellar/common/shortcuts.py
ellar/common/types.py
ellar/common/compatible/__init__.py
ellar/common/compatible/cache_properties.py
ellar/common/compatible/dict.py
ellar/common/decorators/__init__.py
ellar-0.9.5.dist-info/licenses/LICENSE
ellar-0.9.5.dist-info/WHEEL
ellar-0.9.5.dist-info/METADATA
ellar-0.9.5.dist-info/RECORD
