Metadata-Version: 2.4
Name: ellar
Version: 0.9.5
Summary: Ellar - Python ASGI web framework for building fast, efficient, and scalable RESTful APIs and server-side applications.
Author-email: Ezeudoh Tochukwu <tochukwu.ezeudoh@gmail.com>
Requires-Python: >=3.9
Classifier: Intended Audience :: Information Technology
Classifier: Intended Audience :: System Administrators
Classifier: Operating System :: OS Independent
Classifier: Topic :: Internet
Classifier: Topic :: Software Development :: Libraries :: Application Frameworks
Classifier: Topic :: Software Development :: Libraries :: Python Modules
Classifier: Topic :: Software Development :: Libraries
Classifier: Topic :: Software Development
Classifier: Typing :: Typed
Classifier: Environment :: Web Environment
Classifier: Intended Audience :: Developers
Classifier: License :: OSI Approved :: MIT License
Classifier: Programming Language :: Python :: 3
Classifier: Programming Language :: Python :: 3.8
Classifier: Programming Language :: Python :: 3.9
Classifier: Programming Language :: Python :: 3.10
Classifier: Programming Language :: Python :: 3.11
Classifier: Programming Language :: Python :: 3.12
Classifier: Programming Language :: Python :: 3 :: Only
Classifier: Framework :: AsyncIO
Classifier: Topic :: Internet :: WWW/HTTP :: HTTP Servers
Classifier: Topic :: Internet :: WWW/HTTP
License-File: LICENSE
Requires-Dist: injector == 0.22.0
Requires-Dist: starlette == 0.49.1
Requires-Dist: pydantic >=2.5.1,<3.0.0
Requires-Dist: typing-extensions>=4.8.0
Requires-Dist: jinja2
Requires-Dist: python-multipart >=0.0.5,<0.0.21 ; extra == "all"
Requires-Dist: itsdangerous >=1.1.0,<3.0.0 ; extra == "all"
Requires-Dist: pyyaml >=5.3.1,<7.0.0 ; extra == "all"
Requires-Dist: ujson >=4.0.1,!=4.0.2,!=4.1.0,!=4.2.0,!=4.3.0,!=5.0.0,!=5.1.0,<6.0.0 ; extra == "all"
Requires-Dist: orjson >=3.2.1,<4.0.0 ; extra == "all"
Requires-Dist: email_validator >=2.0.0 ; extra == "all"
Requires-Dist: httpx >= 0.22.0 ; extra == "all"
Requires-Dist: passlib >= 1.7.4 ; extra == "all"
Project-URL: Bug Tracker, https://github.com/python-ellar/ellar/issues
Project-URL: Documentation, https://python-ellar.github.io/ellar/
Project-URL: Homepage, https://python-ellar.github.io/ellar/
Project-URL: Source, https://github.com/python-ellar/ellar
Provides-Extra: all
